__init__.py
setup.py
build/lib/__init__.py
build/lib/setup.py
build/lib/hellokrshubh/__init__.py
build/lib/hellokrshubh/libcalculatorpython.cp311-win_amd64.pyd
build/lib/hellokrshubh/libcalculatorpython.cp37-win_amd64.pyd
build/lib/hellokrshubh/libcalculatorpython.cp39-win_amd64.pyd
build/lib/hellokrshubh/libcalculatorpython.cpython-311-darwin.so
hellokrshubh/__init__.py
hellokrshubh/libcalculatorpython.cp311-win_amd64.pyd
hellokrshubh/libcalculatorpython.cp37-win_amd64.pyd
hellokrshubh/libcalculatorpython.cp39-win_amd64.pyd
hellokrshubh/libcalculatorpython.cpython-311-darwin.so
hellokrshubh-0.0.20.dist-info/METADATA
hellokrshubh-0.0.20.dist-info/WHEEL
hellokrshubh-0.0.20.dist-info/top_level.txt
hellokrshubh-0.0.20.dist-info/RECORD
