Metadata-Version: 2.1
Name: hellokrshubh
Version: 0.0.20
Summary: calculator with sum, subtract, multiply, divide and square
Author: Shubham Kumar
Author-email: shubham2021996@gmail.com
Keywords: python
Classifier: Development Status :: 1 - Planning
Classifier: Intended Audience :: Developers
Classifier: Programming Language :: Python :: 3
Classifier: Operating System :: Unix
Classifier: Operating System :: MacOS :: MacOS X
Classifier: Operating System :: Microsoft :: Windows
